{"Austria":{"name":"Austria","url":"https://www.bergfex.com/oesterreich/schneewerte/","resorts":[{"resortName":"Aflenzer Bürgeralm","searchName":"Aflenzer Burgeralm","handle":"aflenzer-burgeralm","snowBottom":null,"snowTop":null,"newSnow":null,"lifts":null},{"resortName":"Alpbach - Ski Juwel Alpbachtal Wildschönau","searchName":"Alpbach - Ski Juwel Alpbachtal Wildschonau","handle":"alpbach-ski-juwel-alpbachtal-wildschonau","snowBottom":null,"snowTop":null,"newSnow":null,"lifts":46},{"resortName":"Annaberg - Lungötz - Dachstein West","searchName":"Annaberg - Lungotz - Dachstein West","handle":"annaberg-lungotz-dachstein-west","snowBottom":null,"snowTop":null,"newSnow":null,"lifts":22},{"resortName":"Axamer Lizum","searchName":"Axamer Lizum","handle":"axamer-lizum","snowBottom":null,"snowTop":null,"newSnow":null,"lifts":null},{"resortName":"Bad Kleinkirchheim","searchName":"Bad Kleinkirchheim","handle":"bad-kleinkirchheim","snowBottom":null,"snowTop":null,"newSnow":null,"lifts":22},{"resortName":"Bergeralm - Steinach am Brenner","searchName":"Bergeralm - Steinach am Brenner","handle":"bergeralm-steinach-am-brenner","snowBottom":null,"snowTop":null,"newSnow":null,"lifts":null},{"resortName":"Berwang","searchName":"Berwang","handle":"berwang","snowBottom":null,"snowTop":null,"newSnow":null,"lifts":null},{"resortName":"Brandlift Scharnitz","searchName":"Brandlift Scharnitz","handle":"brandlift-scharnitz","snowBottom":null,"snowTop":null,"newSnow":null,"lifts":null},{"resortName":"Brandnertal","searchName":"Brandnertal","handle":"brandnertal","snowBottom":null,"snowTop":null,"newSnow":null,"lifts":14},{"resortName":"Dachstein Gletscher Schladming Ramsau - Ski amade","searchName":"Dachstein Gletscher Schladming Ramsau - Ski amade","handle":"dachstein-gletscher-schladming-ramsau-ski-amade","snowBottom":null,"snowTop":null,"newSnow":null,"lifts":5},{"resortName":"Damüls","searchName":"Damuls","handle":"damuls","snowBottom":null,"snowTop":null,"newSnow":null,"lifts":27},{"resortName":"Diedamskopf - Schoppernau","searchName":"Diedamskopf - Schoppernau","handle":"diedamskopf-schoppernau","snowBottom":null,"snowTop":null,"newSnow":null,"lifts":9},{"resortName":"Dorfgastein - Ski amade","searchName":"Dorfgastein - Ski amade","handle":"dorfgastein-ski-amade","snowBottom":null,"snowTop":null,"newSnow":null,"lifts":null},{"resortName":"Dreiländereck - Arnoldstein","searchName":"Dreilandereck - Arnoldstein","handle":"dreilandereck-arnoldstein","snowBottom":null,"snowTop":null,"newSnow":null,"lifts":null},{"resortName":"Eggalm Bahnen - Tux-Lanersbach - Zillertal","searchName":"Eggalm Bahnen - Tux-Lanersbach - Zillertal","handle":"eggalm-bahnen-tux-lanersbach-zillertal","snowBottom":null,"snowTop":25,"newSnow":null,"lifts":68},{"resortName":"Faschina - Fontanella","searchName":"Faschina - Fontanella","handle":"faschina-fontanella","snowBottom":null,"snowTop":null,"newSnow":null,"lifts":28},{"resortName":"Feuerkogel - Ebensee","searchName":"Feuerkogel - Ebensee","handle":"feuerkogel-ebensee","snowBottom":null,"snowTop":null,"newSnow":null,"lifts":8},{"resortName":"Fieberbrunn - Saalbach Hinterglemm Leogang","searchName":"Fieberbrunn - Saalbach Hinterglemm Leogang","handle":"fieberbrunn-saalbach-hinterglemm-leogang","snowBottom":null,"snowTop":null,"newSnow":null,"lifts":70},{"resortName":"Finkenberger Almbahnen - Finkenberg - Zillertal","searchName":"Finkenberger Almbahnen - Finkenberg - Zillertal","handle":"finkenberger-almbahnen-finkenberg-zillertal","snowBottom":null,"snowTop":25,"newSnow":null,"lifts":68},{"resortName":"Flachau - Snow Space Salzburg - Ski amade","searchName":"Flachau - Snow Space Salzburg - Ski amade","handle":"flachau-snow-space-salzburg-ski-amade","snowBottom":null,"snowTop":null,"newSnow":null,"lifts":45},{"resortName":"Freesports Arena Dachstein Krippenstein - Obertraun","searchName":"Freesports Arena Dachstein Krippenstein - Obertraun","handle":"freesports-arena-dachstein-krippenstein-obertraun","snowBottom":null,"snowTop":null,"newSnow":null,"lifts":7},{"resortName":"Gaissau Hintersee","searchName":"Gaissau Hintersee","handle":"gaissau-hintersee","snowBottom":null,"snowTop":null,"newSnow":null,"lifts":null},{"resortName":"Galsterbergalm - Schladming - Ski amade","searchName":"Galsterbergalm - Schladming - Ski amade","handle":"galsterbergalm-schladming-ski-amade","snowBottom":null,"snowTop":null,"newSnow":null,"lifts":null},{"resortName":"Gemeindealpe","searchName":"Gemeindealpe","handle":"gemeindealpe","snowBottom":null,"snowTop":null,"newSnow":null,"lifts":null},{"resortName":"Gerlitzen Alpe","searchName":"Gerlitzen Alpe","handle":"gerlitzen-alpe","snowBottom":null,"snowTop":null,"newSnow":null,"lifts":21},{"resortName":"Golm im Montafon","searchName":"Golm im Montafon","handle":"golm-im-montafon","snowBottom":null,"snowTop":null,"newSnow":null,"lifts":9},{"resortName":"Gosau - Dachstein West","searchName":"Gosau - Dachstein West","handle":"gosau-dachstein-west","snowBottom":null,"snowTop":null,"newSnow":null,"lifts":22},{"resortName":"Großeck - Speiereck - Mauterndorf","searchName":"Großeck - Speiereck - Mauterndorf","handle":"großeck-speiereck-mauterndorf","snowBottom":null,"snowTop":null,"newSnow":null,"lifts":null},{"resortName":"Hauser Kaibling - Schladming - Ski amade","searchName":"Hauser Kaibling - Schladming - Ski amade","handle":"hauser-kaibling-schladming-ski-amade","snowBottom":null,"snowTop":null,"newSnow":null,"lifts":14},{"resortName":"Hinterfeldlift Mösern","searchName":"Hinterfeldlift Mosern","handle":"hinterfeldlift-mosern","snowBottom":null,"snowTop":null,"newSnow":null,"lifts":null},{"resortName":"Hinterstoder - Höss","searchName":"Hinterstoder - Hoss","handle":"hinterstoder-hoss","snowBottom":null,"snowTop":null,"newSnow":null,"lifts":null},{"resortName":"Hintertuxer Gletscher - Hintertux - Zillertal","searchName":"Hintertuxer Gletscher - Hintertux - Zillertal","handle":"hintertuxer-gletscher-hintertux-zillertal","snowBottom":null,"snowTop":25,"newSnow":null,"lifts":21},{"resortName":"Hochficht - Böhmerwald","searchName":"Hochficht - Bohmerwald","handle":"hochficht-bohmerwald","snowBottom":null,"snowTop":null,"newSnow":null,"lifts":null},{"resortName":"Hochfügen - Zillertal","searchName":"Hochfugen - Zillertal","handle":"hochfugen-zillertal","snowBottom":null,"snowTop":null,"newSnow":null,"lifts":null},{"resortName":"Hochkar","searchName":"Hochkar","handle":"hochkar","snowBottom":null,"snowTop":null,"newSnow":null,"lifts":null},{"resortName":"Hochkössen - Unterberg","searchName":"Hochkossen - Unterberg","handle":"hochkossen-unterberg","snowBottom":null,"snowTop":null,"newSnow":null,"lifts":null},{"resortName":"Hochwurzen - Schladming - Ski amade","searchName":"Hochwurzen - Schladming - Ski amade","handle":"hochwurzen-schladming-ski-amade","snowBottom":null,"snowTop":null,"newSnow":null,"lifts":8},{"resortName":"Hochzeiger - Jerzens im Pitztal","searchName":"Hochzeiger - Jerzens im Pitztal","handle":"hochzeiger-jerzens-im-pitztal","snowBottom":null,"snowTop":null,"newSnow":null,"lifts":9},{"resortName":"Imster Bergbahnen","searchName":"Imster Bergbahnen","handle":"imster-bergbahnen","snowBottom":null,"snowTop":null,"newSnow":null,"lifts":4},{"resortName":"Innsbruck Igls - Patscherkofel","searchName":"Innsbruck Igls - Patscherkofel","handle":"innsbruck-igls-patscherkofel","snowBottom":null,"snowTop":null,"newSnow":null,"lifts":null},{"resortName":"Kappl - Paznaun-Ischgl","searchName":"Kappl - Paznaun-Ischgl","handle":"kappl-paznaun-ischgl","snowBottom":null,"snowTop":null,"newSnow":null,"lifts":10},{"resortName":"Kasberg - Grünau im Almtal","searchName":"Kasberg - Grunau im Almtal","handle":"kasberg-grunau-im-almtal","snowBottom":null,"snowTop":null,"newSnow":null,"lifts":null},{"resortName":"Katzenkopf Leutasch","searchName":"Katzenkopf Leutasch","handle":"katzenkopf-leutasch","snowBottom":null,"snowTop":null,"newSnow":null,"lifts":4},{"resortName":"Kitzbühel - Kirchberg","searchName":"Kitzbuhel - Kirchberg","handle":"kitzbuhel-kirchberg","snowBottom":null,"snowTop":null,"newSnow":3,"lifts":56},{"resortName":"Kitzsteinhorn - Kaprun - Kitzsteinhorn","searchName":"Kitzsteinhorn - Kaprun - Kitzsteinhorn","handle":"kitzsteinhorn-kaprun-kitzsteinhorn","snowBottom":null,"snowTop":null,"newSnow":null,"lifts":null},{"resortName":"Königsberg - Hollenstein-Ybbs","searchName":"Konigsberg - Hollenstein-Ybbs","handle":"konigsberg-hollenstein-ybbs","snowBottom":null,"snowTop":null,"newSnow":null,"lifts":null},{"resortName":"Königsleiten - Wald - Zillertal Arena","searchName":"Konigsleiten - Wald - Zillertal Arena","handle":"konigsleiten-wald-zillertal-arena","snowBottom":null,"snowTop":null,"newSnow":null,"lifts":52},{"resortName":"Kreischberg - Murau","searchName":"Kreischberg - Murau","handle":"kreischberg-murau","snowBottom":null,"snowTop":null,"newSnow":null,"lifts":null},{"resortName":"Krimml - Hochkrimml – Zillertal Arena","searchName":"Krimml - Hochkrimml – Zillertal Arena","handle":"krimml-hochkrimml-–-zillertal-arena","snowBottom":null,"snowTop":null,"newSnow":null,"lifts":52},{"resortName":"Kühtai","searchName":"Kuhtai","handle":"kuhtai","snowBottom":null,"snowTop":null,"newSnow":null,"lifts":null},{"resortName":"Lachtal","searchName":"Lachtal","handle":"lachtal","snowBottom":null,"snowTop":null,"newSnow":null,"lifts":null},{"resortName":"Lackenhof - Ötscher","searchName":"Lackenhof - Otscher","handle":"lackenhof-otscher","snowBottom":null,"snowTop":null,"newSnow":null,"lifts":null},{"resortName":"Lienzer Bergbahnen - Zettersfeld-Hochstein","searchName":"Lienzer Bergbahnen - Zettersfeld-Hochstein","handle":"lienzer-bergbahnen-zettersfeld-hochstein","snowBottom":null,"snowTop":null,"newSnow":null,"lifts":null},{"resortName":"Loser - Altaussee - Schneebären","searchName":"Loser - Altaussee - Schneebaren","handle":"loser-altaussee-schneebaren","snowBottom":null,"snowTop":null,"newSnow":null,"lifts":null},{"resortName":"Maiskogel - Kaprun - Kitzsteinhorn","searchName":"Maiskogel - Kaprun - Kitzsteinhorn","handle":"maiskogel-kaprun-kitzsteinhorn","snowBottom":null,"snowTop":null,"newSnow":null,"lifts":null},{"resortName":"Mellau - Damüls - Faschina Skischaukel","searchName":"Mellau - Damuls - Faschina Skischaukel","handle":"mellau-damuls-faschina-skischaukel","snowBottom":null,"snowTop":null,"newSnow":null,"lifts":27},{"resortName":"Nassfeld","searchName":"Nassfeld","handle":"nassfeld","snowBottom":null,"snowTop":null,"newSnow":null,"lifts":null},{"resortName":"Obergurgl - Hochgurgl","searchName":"Obergurgl - Hochgurgl","handle":"obergurgl-hochgurgl","snowBottom":null,"snowTop":null,"newSnow":null,"lifts":null},{"resortName":"Oberperfuss - Rangger Köpfl","searchName":"Oberperfuss - Rangger Kopfl","handle":"oberperfuss-rangger-kopfl","snowBottom":null,"snowTop":null,"newSnow":null,"lifts":null},{"resortName":"Oetz - Hochoetz","searchName":"Oetz - Hochoetz","handle":"oetz-hochoetz","snowBottom":null,"snowTop":null,"newSnow":null,"lifts":13},{"resortName":"Panoramabahn Kitzbüheler Alpen - Mittersill","searchName":"Panoramabahn Kitzbuheler Alpen - Mittersill","handle":"panoramabahn-kitzbuheler-alpen-mittersill","snowBottom":null,"snowTop":null,"newSnow":3,"lifts":56},{"resortName":"Pitztaler Gletscher - Rifflsee - Pitztal","searchName":"Pitztaler Gletscher - Rifflsee - Pitztal","handle":"pitztaler-gletscher-rifflsee-pitztal","snowBottom":null,"snowTop":55,"newSnow":null,"lifts":12},{"resortName":"Planai - Schladming - Ski amade","searchName":"Planai - Schladming - Ski amade","handle":"planai-schladming-ski-amade","snowBottom":null,"snowTop":null,"newSnow":null,"lifts":14},{"resortName":"Ramsau - Dachstein - Ski amade","searchName":"Ramsau - Dachstein - Ski amade","handle":"ramsau-dachstein-ski-amade","snowBottom":null,"snowTop":null,"newSnow":null,"lifts":null},{"resortName":"Rastkogel Bahnen - Tux-Vorderlanersbach - Zillertal","searchName":"Rastkogel Bahnen - Tux-Vorderlanersbach - Zillertal","handle":"rastkogel-bahnen-tux-vorderlanersbach-zillertal","snowBottom":null,"snowTop":25,"newSnow":null,"lifts":68},{"resortName":"Raurisertal - Hochalmbahnen","searchName":"Raurisertal - Hochalmbahnen","handle":"raurisertal-hochalmbahnen","snowBottom":null,"snowTop":null,"newSnow":null,"lifts":10},{"resortName":"Riesneralm - Schneebären","searchName":"Riesneralm - Schneebaren","handle":"riesneralm-schneebaren","snowBottom":null,"snowTop":null,"newSnow":null,"lifts":null},{"resortName":"Rußbach am Paß Gschütt - Dachstein West","searchName":"Rußbach am Paß Gschutt - Dachstein West","handle":"rußbach-am-paß-gschutt-dachstein-west","snowBottom":null,"snowTop":null,"newSnow":null,"lifts":22},{"resortName":"Saalbach Hinterglemm Leogang Fieberbrunn","searchName":"Saalbach Hinterglemm Leogang Fieberbrunn","handle":"saalbach-hinterglemm-leogang-fieberbrunn","snowBottom":null,"snowTop":null,"newSnow":null,"lifts":70},{"resortName":"Schlepplifte Neuleutasch","searchName":"Schlepplifte Neuleutasch","handle":"schlepplifte-neuleutasch","snowBottom":null,"snowTop":null,"newSnow":null,"lifts":null},{"resortName":"Schmitten - Zell am See","searchName":"Schmitten - Zell am See","handle":"schmitten-zell-am-see","snowBottom":null,"snowTop":null,"newSnow":null,"lifts":28},{"resortName":"See - Paznaun-Ischgl","searchName":"See - Paznaun-Ischgl","handle":"see-paznaun-ischgl","snowBottom":null,"snowTop":null,"newSnow":null,"lifts":12},{"resortName":"Seefeld - Birkenlift & Geigenbühellift","searchName":"Seefeld - Birkenlift & Geigenbuhellift","handle":"seefeld-birkenlift-&-geigenbuhellift","snowBottom":null,"snowTop":null,"newSnow":null,"lifts":null},{"resortName":"Seefeld - Rosshütte","searchName":"Seefeld - Rosshutte","handle":"seefeld-rosshutte","snowBottom":null,"snowTop":null,"newSnow":null,"lifts":14},{"resortName":"Serlesbahnen Mieders","searchName":"Serlesbahnen Mieders","handle":"serlesbahnen-mieders","snowBottom":null,"snowTop":null,"newSnow":null,"lifts":5},{"resortName":"Silvapark Galtür - Paznaun-Ischgl","searchName":"Silvapark Galtur - Paznaun-Ischgl","handle":"silvapark-galtur-paznaun-ischgl","snowBottom":null,"snowTop":null,"newSnow":null,"lifts":null},{"resortName":"Silvretta Arena Ischgl - Samnaun","searchName":"Silvretta Arena Ischgl - Samnaun","handle":"silvretta-arena-ischgl-samnaun","snowBottom":null,"snowTop":null,"newSnow":null,"lifts":45},{"resortName":"Silvretta Bielerhöhe im Montafon","searchName":"Silvretta Bielerhohe im Montafon","handle":"silvretta-bielerhohe-im-montafon","snowBottom":null,"snowTop":null,"newSnow":null,"lifts":3},{"resortName":"Silvretta Montafon","searchName":"Silvretta Montafon","handle":"silvretta-montafon","snowBottom":null,"snowTop":null,"newSnow":null,"lifts":36},{"resortName":"Ski- und Gletscherwelt Zillertal 3000 - Zillertal","searchName":"Ski- und Gletscherwelt Zillertal 3000 - Zillertal","handle":"ski--und-gletscherwelt-zillertal-3000-zillertal","snowBottom":null,"snowTop":25,"newSnow":null,"lifts":68},{"resortName":"Sölden","searchName":"Solden","handle":"solden","snowBottom":null,"snowTop":72,"newSnow":null,"lifts":32},{"resortName":"Spechtenseelift - Wörschachwald","searchName":"Spechtenseelift - Worschachwald","handle":"spechtenseelift-worschachwald","snowBottom":null,"snowTop":null,"newSnow":null,"lifts":null},{"resortName":"St. Johann - Alpendorf - Snow Space Salzburg - Ski amade","searchName":"St. Johann - Alpendorf - Snow Space Salzburg - Ski amade","handle":"st-johann-alpendorf-snow-space-salzburg-ski-amade","snowBottom":null,"snowTop":null,"newSnow":null,"lifts":45},{"resortName":"Stubaier Gletscher - Stubaital","searchName":"Stubaier Gletscher - Stubaital","handle":"stubaier-gletscher-stubaital","snowBottom":null,"snowTop":15,"newSnow":null,"lifts":null},{"resortName":"Stuhleck - Semmering","searchName":"Stuhleck - Semmering","handle":"stuhleck-semmering","snowBottom":null,"snowTop":null,"newSnow":null,"lifts":null},{"resortName":"Tauplitz - Bad Mitterndorf - Schneebären","searchName":"Tauplitz - Bad Mitterndorf - Schneebaren","handle":"tauplitz-bad-mitterndorf-schneebaren","snowBottom":null,"snowTop":null,"newSnow":null,"lifts":null},{"resortName":"Turracher Höhe","searchName":"Turracher Hohe","handle":"turracher-hohe","snowBottom":null,"snowTop":null,"newSnow":null,"lifts":14},{"resortName":"Vent","searchName":"Vent","handle":"vent","snowBottom":null,"snowTop":null,"newSnow":null,"lifts":null},{"resortName":"Wagrain - Snow Space Salzburg - Ski amade","searchName":"Wagrain - Snow Space Salzburg - Ski amade","handle":"wagrain-snow-space-salzburg-ski-amade","snowBottom":null,"snowTop":null,"newSnow":null,"lifts":45},{"resortName":"Waidring - Steinplatte","searchName":"Waidring - Steinplatte","handle":"waidring-steinplatte","snowBottom":null,"snowTop":null,"newSnow":null,"lifts":14},{"resortName":"Weissensee","searchName":"Weissensee","handle":"weissensee","snowBottom":null,"snowTop":null,"newSnow":null,"lifts":null},{"resortName":"Werfenweng","searchName":"Werfenweng","handle":"werfenweng","snowBottom":null,"snowTop":null,"newSnow":null,"lifts":null},{"resortName":"Wildkogel-Arena - Neukirchen - Bramberg","searchName":"Wildkogel-Arena - Neukirchen - Bramberg","handle":"wildkogel-arena-neukirchen-bramberg","snowBottom":null,"snowTop":null,"newSnow":null,"lifts":20},{"resortName":"Wildschönau - Ski Juwel Alpbachtal Wildschönau","searchName":"Wildschonau - Ski Juwel Alpbachtal Wildschonau","handle":"wildschonau-ski-juwel-alpbachtal-wildschonau","snowBottom":null,"snowTop":null,"newSnow":null,"lifts":46},{"resortName":"Wurzeralm - Spital am Pyhrn","searchName":"Wurzeralm - Spital am Pyhrn","handle":"wurzeralm-spital-am-pyhrn","snowBottom":null,"snowTop":null,"newSnow":null,"lifts":8},{"resortName":"Zillertal Arena - Gerlos - Zillertal","searchName":"Zillertal Arena - Gerlos - Zillertal","handle":"zillertal-arena-gerlos-zillertal","snowBottom":null,"snowTop":null,"newSnow":null,"lifts":52},{"resortName":"Zillertal Arena - Gerlosstein-Hainzenberg - Zillertal","searchName":"Zillertal Arena - Gerlosstein-Hainzenberg - Zillertal","handle":"zillertal-arena-gerlosstein-hainzenberg-zillertal","snowBottom":null,"snowTop":null,"newSnow":null,"lifts":52},{"resortName":"Zillertal Arena - Zell am Ziller - Zillertal","searchName":"Zillertal Arena - Zell am Ziller - Zillertal","handle":"zillertal-arena-zell-am-ziller-zillertal","snowBottom":null,"snowTop":null,"newSnow":null,"lifts":52}]},"Switzerland":{"name":"Switzerland","url":"https://www.bergfex.com/schweiz/schneewerte/","resorts":[{"resortName":"Andermatt - Oberalp - Sedrun","searchName":"Andermatt - Oberalp - Sedrun","handle":"andermatt-oberalp-sedrun","snowBottom":null,"snowTop":null,"newSnow":null,"lifts":null},{"resortName":"Bellwald","searchName":"Bellwald","handle":"bellwald","snowBottom":null,"snowTop":null,"newSnow":null,"lifts":null},{"resortName":"Bivio","searchName":"Bivio","handle":"bivio","snowBottom":null,"snowTop":null,"newSnow":null,"lifts":null},{"resortName":"Elm","searchName":"Elm","handle":"elm","snowBottom":null,"snowTop":null,"newSnow":null,"lifts":6},{"resortName":"Lauchernalp - Lötschental","searchName":"Lauchernalp - Lotschental","handle":"lauchernalp-lotschental","snowBottom":null,"snowTop":null,"newSnow":null,"lifts":7},{"resortName":"Les Diablerets - Glacier 3000","searchName":"Les Diablerets - Glacier 3000","handle":"les-diablerets-glacier-3000","snowBottom":null,"snowTop":35,"newSnow":null,"lifts":null},{"resortName":"Pian Cales - San Bernardino","searchName":"Pian Cales - San Bernardino","handle":"pian-cales-san-bernardino","snowBottom":null,"snowTop":null,"newSnow":null,"lifts":null},{"resortName":"Saas Almagell","searchName":"Saas Almagell","handle":"saas-almagell","snowBottom":null,"snowTop":null,"newSnow":null,"lifts":7},{"resortName":"Saas-Fee","searchName":"Saas-Fee","handle":"saas-fee","snowBottom":null,"snowTop":null,"newSnow":null,"lifts":22},{"resortName":"Savognin","searchName":"Savognin","handle":"savognin","snowBottom":null,"snowTop":null,"newSnow":null,"lifts":12},{"resortName":"Scuol Motta Naluns","searchName":"Scuol Motta Naluns","handle":"scuol-motta-naluns","snowBottom":null,"snowTop":9,"newSnow":null,"lifts":null},{"resortName":"Silvretta Arena Samnaun - Ischgl","searchName":"Silvretta Arena Samnaun - Ischgl","handle":"silvretta-arena-samnaun-ischgl","snowBottom":null,"snowTop":null,"newSnow":null,"lifts":45},{"resortName":"Zermatt","searchName":"Zermatt","handle":"zermatt","snowBottom":null,"snowTop":12,"newSnow":null,"lifts":48}]},"Germany":{"name":"Germany","url":"https://www.bergfex.com/deutschland/schneewerte/","resorts":[{"resortName":"Balderschwang","searchName":"Balderschwang","handle":"balderschwang","snowBottom":null,"snowTop":null,"newSnow":null,"lifts":null},{"resortName":"Brauneck - Lenggries","searchName":"Brauneck - Lenggries","handle":"brauneck-lenggries","snowBottom":null,"snowTop":null,"newSnow":null,"lifts":15},{"resortName":"Garmisch-Classic","searchName":"Garmisch-Classic","handle":"garmisch-classic","snowBottom":null,"snowTop":null,"newSnow":null,"lifts":17},{"resortName":"Geisskopf","searchName":"Geisskopf","handle":"geisskopf","snowBottom":null,"snowTop":null,"newSnow":null,"lifts":null},{"resortName":"Großer Arber","searchName":"Großer Arber","handle":"großer-arber","snowBottom":null,"snowTop":null,"newSnow":null,"lifts":5},{"resortName":"Hochschwarzeck - Ramsau bei Berchtesgaden","searchName":"Hochschwarzeck - Ramsau bei Berchtesgaden","handle":"hochschwarzeck-ramsau-bei-berchtesgaden","snowBottom":null,"snowTop":null,"newSnow":null,"lifts":3},{"resortName":"Mittenwald - Kranzberg","searchName":"Mittenwald - Kranzberg","handle":"mittenwald-kranzberg","snowBottom":null,"snowTop":null,"newSnow":null,"lifts":null},{"resortName":"Skilift Beiningen","searchName":"Skilift Beiningen","handle":"skilift-beiningen","snowBottom":null,"snowTop":null,"newSnow":null,"lifts":null},{"resortName":"Skizentrum Pfronten - Steinach","searchName":"Skizentrum Pfronten - Steinach","handle":"skizentrum-pfronten-steinach","snowBottom":null,"snowTop":null,"newSnow":null,"lifts":null},{"resortName":"Spitzingsee - Tegernsee","searchName":"Spitzingsee - Tegernsee","handle":"spitzingsee-tegernsee","snowBottom":null,"snowTop":null,"newSnow":null,"lifts":10},{"resortName":"Sudelfeld - Bayrischzell","searchName":"Sudelfeld - Bayrischzell","handle":"sudelfeld-bayrischzell","snowBottom":null,"snowTop":null,"newSnow":null,"lifts":null},{"resortName":"Wallberg Tegernseer Tal","searchName":"Wallberg Tegernseer Tal","handle":"wallberg-tegernseer-tal","snowBottom":null,"snowTop":null,"newSnow":null,"lifts":1},{"resortName":"Zugspitze","searchName":"Zugspitze","handle":"zugspitze","snowBottom":2,"snowTop":null,"newSnow":null,"lifts":8}]},"Italy":{"name":"Italy","url":"https://www.bergfex.com/italien/schneewerte/","resorts":[{"resortName":"3 Zinnen Dolomiten","searchName":"3 Zinnen Dolomiten","handle":"3-zinnen-dolomiten","snowBottom":null,"snowTop":null,"newSnow":null,"lifts":31},{"resortName":"Alta Badia","searchName":"Alta Badia","handle":"alta-badia","snowBottom":null,"snowTop":null,"newSnow":null,"lifts":58},{"resortName":"Arabba","searchName":"Arabba","handle":"arabba","snowBottom":24,"snowTop":null,"newSnow":null,"lifts":22},{"resortName":"Campitello - Col Rodella - Val di Fassa","searchName":"Campitello - Col Rodella - Val di Fassa","handle":"campitello-col-rodella-val-di-fassa","snowBottom":null,"snowTop":null,"newSnow":null,"lifts":null},{"resortName":"Carezza - Karersee - Rosengarten","searchName":"Carezza - Karersee - Rosengarten","handle":"carezza-karersee-rosengarten","snowBottom":null,"snowTop":null,"newSnow":null,"lifts":13},{"resortName":"Carosello 3000- Livigno","searchName":"Carosello 3000- Livigno","handle":"carosello-3000--livigno","snowBottom":null,"snowTop":null,"newSnow":null,"lifts":null},{"resortName":"Cesana - Sansicario - Via Lattea","searchName":"Cesana - Sansicario - Via Lattea","handle":"cesana-sansicario-via-lattea","snowBottom":null,"snowTop":null,"newSnow":null,"lifts":null},{"resortName":"Chiesa Valmalenco - Alpe Palù","searchName":"Chiesa Valmalenco - Alpe Palu","handle":"chiesa-valmalenco-alpe-palu","snowBottom":null,"snowTop":null,"newSnow":null,"lifts":null},{"resortName":"Claviere - Via Lattea","searchName":"Claviere - Via Lattea","handle":"claviere-via-lattea","snowBottom":null,"snowTop":null,"newSnow":null,"lifts":null},{"resortName":"Dolomites Val Gardena - Gröden - St. Christina","searchName":"Dolomites Val Gardena - Groden - St. Christina","handle":"dolomites-val-gardena-groden-st-christina","snowBottom":null,"snowTop":null,"newSnow":null,"lifts":7},{"resortName":"Dolomites Val Gardena - Gröden - St. Ulrich","searchName":"Dolomites Val Gardena - Groden - St. Ulrich","handle":"dolomites-val-gardena-groden-st-ulrich","snowBottom":null,"snowTop":null,"newSnow":null,"lifts":12},{"resortName":"Dolomites Val Gardena - Gröden - Wolkenstein","searchName":"Dolomites Val Gardena - Groden - Wolkenstein","handle":"dolomites-val-gardena-groden-wolkenstein","snowBottom":null,"snowTop":null,"newSnow":null,"lifts":40},{"resortName":"Faloria - Monte Cristallo - Mietres","searchName":"Faloria - Monte Cristallo - Mietres","handle":"faloria-monte-cristallo-mietres","snowBottom":null,"snowTop":null,"newSnow":null,"lifts":null},{"resortName":"Gitschberg Jochtal","searchName":"Gitschberg Jochtal","handle":"gitschberg-jochtal","snowBottom":null,"snowTop":null,"newSnow":null,"lifts":15},{"resortName":"Jochgrimm","searchName":"Jochgrimm","handle":"jochgrimm","snowBottom":null,"snowTop":null,"newSnow":null,"lifts":null},{"resortName":"Klausberg - Ahrntal","searchName":"Klausberg - Ahrntal","handle":"klausberg-ahrntal","snowBottom":34,"snowTop":96,"newSnow":null,"lifts":11},{"resortName":"Kronplatz - Dolomiten","searchName":"Kronplatz - Dolomiten","handle":"kronplatz-dolomiten","snowBottom":null,"snowTop":null,"newSnow":null,"lifts":37},{"resortName":"Ladurns - Pflerschtal","searchName":"Ladurns - Pflerschtal","handle":"ladurns-pflerschtal","snowBottom":null,"snowTop":null,"newSnow":null,"lifts":4},{"resortName":"Maseben - Langtaufers - Reschenpass","searchName":"Maseben - Langtaufers - Reschenpass","handle":"maseben-langtaufers-reschenpass","snowBottom":50,"snowTop":150,"newSnow":null,"lifts":null},{"resortName":"Meran 2000","searchName":"Meran 2000","handle":"meran-2000","snowBottom":null,"snowTop":null,"newSnow":null,"lifts":8},{"resortName":"Mottolino Fun Mountain- Livigno","searchName":"Mottolino Fun Mountain- Livigno","handle":"mottolino-fun-mountain--livigno","snowBottom":null,"snowTop":null,"newSnow":null,"lifts":null},{"resortName":"Paganella - Andalo","searchName":"Paganella - Andalo","handle":"paganella-andalo","snowBottom":null,"snowTop":null,"newSnow":null,"lifts":19},{"resortName":"Pfelders im Passeiertal","searchName":"Pfelders im Passeiertal","handle":"pfelders-im-passeiertal","snowBottom":null,"snowTop":null,"newSnow":null,"lifts":null},{"resortName":"Plose Brixen","searchName":"Plose Brixen","handle":"plose-brixen","snowBottom":null,"snowTop":null,"newSnow":null,"lifts":7},{"resortName":"Pozza di Fassa - Buffaure - Val di Fassa","searchName":"Pozza di Fassa - Buffaure - Val di Fassa","handle":"pozza-di-fassa-buffaure-val-di-fassa","snowBottom":null,"snowTop":null,"newSnow":null,"lifts":null},{"resortName":"Pragelato - Via Lattea","searchName":"Pragelato - Via Lattea","handle":"pragelato-via-lattea","snowBottom":null,"snowTop":null,"newSnow":null,"lifts":null},{"resortName":"Ratschings Jaufen","searchName":"Ratschings Jaufen","handle":"ratschings-jaufen","snowBottom":5,"snowTop":10,"newSnow":null,"lifts":8},{"resortName":"Reinswald Sarntal","searchName":"Reinswald Sarntal","handle":"reinswald-sarntal","snowBottom":5,"snowTop":null,"newSnow":null,"lifts":null},{"resortName":"Rittner Horn","searchName":"Rittner Horn","handle":"rittner-horn","snowBottom":null,"snowTop":null,"newSnow":null,"lifts":5},{"resortName":"Rosskopf - Sterzing","searchName":"Rosskopf - Sterzing","handle":"rosskopf-sterzing","snowBottom":null,"snowTop":60,"newSnow":null,"lifts":null},{"resortName":"Sauze d'Oulx - Via Lattea","searchName":"Sauze d'Oulx - Via Lattea","handle":"sauze-d'oulx-via-lattea","snowBottom":null,"snowTop":null,"newSnow":null,"lifts":null},{"resortName":"Schöneben - Haideralm - Reschenpass","searchName":"Schoneben - Haideralm - Reschenpass","handle":"schoneben-haideralm-reschenpass","snowBottom":30,"snowTop":150,"newSnow":null,"lifts":12},{"resortName":"Schwemmalm - Ultental","searchName":"Schwemmalm - Ultental","handle":"schwemmalm-ultental","snowBottom":15,"snowTop":40,"newSnow":null,"lifts":null},{"resortName":"Seiser Alm","searchName":"Seiser Alm","handle":"seiser-alm","snowBottom":null,"snowTop":null,"newSnow":null,"lifts":22},{"resortName":"Speikboden - Tauferer Ahrntal","searchName":"Speikboden - Tauferer Ahrntal","handle":"speikboden-tauferer-ahrntal","snowBottom":null,"snowTop":null,"newSnow":null,"lifts":8},{"resortName":"Trafoi am Ortler - Furkel","searchName":"Trafoi am Ortler - Furkel","handle":"trafoi-am-ortler-furkel","snowBottom":90,"snowTop":90,"newSnow":null,"lifts":null},{"resortName":"Vigiljoch - Lana","searchName":"Vigiljoch - Lana","handle":"vigiljoch-lana","snowBottom":null,"snowTop":null,"newSnow":null,"lifts":4},{"resortName":"Villnöss","searchName":"Villnoss","handle":"villnoss","snowBottom":null,"snowTop":null,"newSnow":null,"lifts":null},{"resortName":"Watles","searchName":"Watles","handle":"watles","snowBottom":80,"snowTop":100,"newSnow":null,"lifts":3}]},"Slovenia":{"name":"Slovenia","url":"https://www.bergfex.com/slovenia/schneewerte/","resorts":[{"resortName":"Bukovnik","searchName":"Bukovnik","handle":"bukovnik","snowBottom":null,"snowTop":30,"newSnow":null,"lifts":null},{"resortName":"Krvavec","searchName":"Krvavec","handle":"krvavec","snowBottom":null,"snowTop":null,"newSnow":null,"lifts":null},{"resortName":"Rogla","searchName":"Rogla","handle":"rogla","snowBottom":null,"snowTop":null,"newSnow":null,"lifts":null},{"resortName":"Stari vrh","searchName":"Stari vrh","handle":"stari-vrh","snowBottom":null,"snowTop":null,"newSnow":null,"lifts":null},{"resortName":"Vogel","searchName":"Vogel","handle":"vogel","snowBottom":null,"snowTop":null,"newSnow":null,"lifts":9}]},"France":{"name":"France","url":"https://www.bergfex.com/frankreich/schneewerte/","resorts":[{"resortName":"Brides-les-Bains - Les 3 Vallées","searchName":"Brides-les-Bains - Les 3 Vallees","handle":"brides-les-bains-les-3-vallees","snowBottom":null,"snowTop":null,"newSnow":null,"lifts":null},{"resortName":"Champ Du Feu","searchName":"Champ Du Feu","handle":"champ-du-feu","snowBottom":null,"snowTop":null,"newSnow":null,"lifts":null},{"resortName":"Gérardmer","searchName":"Gerardmer","handle":"gerardmer","snowBottom":null,"snowTop":null,"newSnow":null,"lifts":null},{"resortName":"Lac Blanc","searchName":"Lac Blanc","handle":"lac-blanc","snowBottom":null,"snowTop":null,"newSnow":null,"lifts":null},{"resortName":"Orelle Val Thorens - Les 3 Vallées","searchName":"Orelle Val Thorens - Les 3 Vallees","handle":"orelle-val-thorens-les-3-vallees","snowBottom":null,"snowTop":null,"newSnow":null,"lifts":null},{"resortName":"Station des Rousses - Jura sur Léman","searchName":"Station des Rousses - Jura sur Leman","handle":"station-des-rousses-jura-sur-leman","snowBottom":null,"snowTop":null,"newSnow":null,"lifts":null},{"resortName":"Val Thorens - Les 3 Vallées","searchName":"Val Thorens - Les 3 Vallees","handle":"val-thorens-les-3-vallees","snowBottom":null,"snowTop":null,"newSnow":null,"lifts":null}]},"CzechRepublic":{"name":"Czech Republic","url":"https://www.bergfex.com/czechia/schneewerte/","resorts":[{"resortName":"Monínec","searchName":"Moninec","handle":"moninec","snowBottom":null,"snowTop":null,"newSnow":null,"lifts":null}]},"Slovakia":{"name":"Slovakia","url":"https://www.bergfex.com/slovakia/schneewerte/","resorts":[]},"Spain":{"name":"Spain","url":"https://www.bergfex.com/spanien/schneewerte/","resorts":[]},"Liechtenstein":{"name":"Liechtenstein","url":"https://www.bergfex.com/liechtenstein/schneewerte/","resorts":[]},"Norway":{"name":"Norway","url":"https://www.onthesnow.co.uk/norway/skireport","resorts":[{"resortName":"Beitostølen2022 Dec 10","searchName":"Beitostølen2022 Dec 10","handle":"beitostølen2022-dec-10","newSnow":0,"snowBottom":null,"snowTop":null,"lifts":null},{"resortName":"Bjorli Skisenter AS 2022 Nov 01","searchName":"Bjorli Skisenter AS 2022 Nov 01","handle":"bjorli-skisenter-as-2022-nov-01","newSnow":0,"snowBottom":null,"snowTop":0,"lifts":null},{"resortName":"Gausta Skisenter2022 Dec 03","searchName":"Gausta Skisenter2022 Dec 03","handle":"gausta-skisenter2022-dec-03","newSnow":0,"snowBottom":0,"snowTop":0,"lifts":null},{"resortName":"Geilo2022 Dec 03","searchName":"Geilo2022 Dec 03","handle":"geilo2022-dec-03","newSnow":0,"snowBottom":0,"snowTop":0,"lifts":null},{"resortName":"Gålå2022 Dec 17","searchName":"Gala2022 Dec 17","handle":"gala2022-dec-17","newSnow":0,"snowBottom":0,"snowTop":0,"lifts":null},{"resortName":"Hafjell2022 Dec 03","searchName":"Hafjell2022 Dec 03","handle":"hafjell2022-dec-03","newSnow":0,"snowBottom":null,"snowTop":null,"lifts":null},{"resortName":"Hemsedal2022 Dec 03","searchName":"Hemsedal2022 Dec 03","handle":"hemsedal2022-dec-03","newSnow":0,"snowBottom":0,"snowTop":0,"lifts":null},{"resortName":"Kongsberg2022 Dec 03","searchName":"Kongsberg2022 Dec 03","handle":"kongsberg2022-dec-03","newSnow":0,"snowBottom":null,"snowTop":null,"lifts":null},{"resortName":"Kvitfjell2022 Dec 03","searchName":"Kvitfjell2022 Dec 03","handle":"kvitfjell2022-dec-03","newSnow":0,"snowBottom":0,"snowTop":0,"lifts":null},{"resortName":"Norefjell2022 Dec 10","searchName":"Norefjell2022 Dec 10","handle":"norefjell2022-dec-10","newSnow":0,"snowBottom":null,"snowTop":null,"lifts":null},{"resortName":"Stranda2022 Dec 17","searchName":"Stranda2022 Dec 17","handle":"stranda2022-dec-17","newSnow":0,"snowBottom":null,"snowTop":null,"lifts":null},{"resortName":"Oppdal2022 Dec 09","searchName":"Oppdal2022 Dec 09","handle":"oppdal2022-dec-09","newSnow":0,"snowBottom":0,"snowTop":0,"lifts":null},{"resortName":"Sunnmørsalpane2022 Dec 09","searchName":"Sunnmørsalpane2022 Dec 09","handle":"sunnmørsalpane2022-dec-09","newSnow":0,"snowBottom":null,"snowTop":0,"lifts":null},{"resortName":"Oslo Vinterpark - Tryvann2022 Dec 10","searchName":"Oslo Vinterpark - Tryvann2022 Dec 10","handle":"oslo-vinterpark-tryvann2022-dec-10","newSnow":0,"snowBottom":null,"snowTop":null,"lifts":null},{"resortName":"Sirdal2022 Dec 23","searchName":"Sirdal2022 Dec 23","handle":"sirdal2022-dec-23","newSnow":0,"snowBottom":null,"snowTop":null,"lifts":null},{"resortName":"Roldal2022 Dec 17","searchName":"Roldal2022 Dec 17","handle":"roldal2022-dec-17","newSnow":0,"snowBottom":null,"snowTop":null,"lifts":null},{"resortName":"Lifjell Skisenter2022 Dec 03","searchName":"Lifjell Skisenter2022 Dec 03","handle":"lifjell-skisenter2022-dec-03","newSnow":0,"snowBottom":null,"snowTop":null,"lifts":null},{"resortName":"Hallingskarvet2023 Jan 06","searchName":"Hallingskarvet2023 Jan 06","handle":"hallingskarvet2023-jan-06","newSnow":0,"snowBottom":null,"snowTop":0,"lifts":null},{"resortName":"Drammen2022 Dec 17","searchName":"Drammen2022 Dec 17","handle":"drammen2022-dec-17","newSnow":0,"snowBottom":0,"snowTop":0,"lifts":null},{"resortName":"Grong2023 Jan 07","searchName":"Grong2023 Jan 07","handle":"grong2023-jan-07","newSnow":0,"snowBottom":null,"snowTop":null,"lifts":null},{"resortName":"Harpefossen2023 Jan 07","searchName":"Harpefossen2023 Jan 07","handle":"harpefossen2023-jan-07","newSnow":0,"snowBottom":0,"snowTop":0,"lifts":null},{"resortName":"Haukeli Skisenter2022 Dec 10","searchName":"Haukeli Skisenter2022 Dec 10","handle":"haukeli-skisenter2022-dec-10","newSnow":0,"snowBottom":null,"snowTop":null,"lifts":null},{"resortName":"Eikedalen2022 Dec 10","searchName":"Eikedalen2022 Dec 10","handle":"eikedalen2022-dec-10","newSnow":0,"snowBottom":null,"snowTop":0,"lifts":null},{"resortName":"Ljosland2022 Dec 25","searchName":"Ljosland2022 Dec 25","handle":"ljosland2022-dec-25","newSnow":0,"snowBottom":null,"snowTop":null,"lifts":null},{"resortName":"Kirkerudbakken Skisenter2022 Dec 28","searchName":"Kirkerudbakken Skisenter2022 Dec 28","handle":"kirkerudbakken-skisenter2022-dec-28","newSnow":0,"snowBottom":0,"snowTop":0,"lifts":null},{"resortName":"Golsfjellet2023 Feb 18","searchName":"Golsfjellet2023 Feb 18","handle":"golsfjellet2023-feb-18","newSnow":0,"snowBottom":null,"snowTop":null,"lifts":null},{"resortName":"Hurdal Skisenter2022 Dec 31","searchName":"Hurdal Skisenter2022 Dec 31","handle":"hurdal-skisenter2022-dec-31","newSnow":0,"snowBottom":null,"snowTop":null,"lifts":null},{"resortName":"Fulufjellet2022 Dec 17","searchName":"Fulufjellet2022 Dec 17","handle":"fulufjellet2022-dec-17","newSnow":0,"snowBottom":null,"snowTop":null,"lifts":null},{"resortName":"Hovden2022 Dec 09","searchName":"Hovden2022 Dec 09","handle":"hovden2022-dec-09","newSnow":0,"snowBottom":null,"snowTop":null,"lifts":null},{"resortName":"Brokke2022 Dec 17","searchName":"Brokke2022 Dec 17","handle":"brokke2022-dec-17","newSnow":0,"snowBottom":null,"snowTop":0,"lifts":null},{"resortName":"Narvik2022 Dec 10","searchName":"Narvik2022 Dec 10","handle":"narvik2022-dec-10","newSnow":0,"snowBottom":null,"snowTop":null,"lifts":null},{"resortName":"Nesbyen2022 Dec 17","searchName":"Nesbyen2022 Dec 17","handle":"nesbyen2022-dec-17","newSnow":0,"snowBottom":null,"snowTop":null,"lifts":null},{"resortName":"Sjusjøen2022 Dec 03","searchName":"Sjusjøen2022 Dec 03","handle":"sjusjøen2022-dec-03","newSnow":0,"snowBottom":0,"snowTop":0,"lifts":null},{"resortName":"Oslo Skisenter-Grefsen2022 Dec 07","searchName":"Oslo Skisenter-Grefsen2022 Dec 07","handle":"oslo-skisenter-grefsen2022-dec-07","newSnow":0,"snowBottom":null,"snowTop":null,"lifts":null},{"resortName":"Ørsta2023 Jan 21","searchName":"Ørsta2023 Jan 21","handle":"ørsta2023-jan-21","newSnow":0,"snowBottom":0,"snowTop":0,"lifts":null},{"resortName":"Rauland - Raulandsfjell - Vierli2022 Dec 03","searchName":"Rauland - Raulandsfjell - Vierli2022 Dec 03","handle":"rauland-raulandsfjell-vierli2022-dec-03","newSnow":0,"snowBottom":null,"snowTop":0,"lifts":null},{"resortName":"Budor2023 Jan 28","searchName":"Budor2023 Jan 28","handle":"budor2023-jan-28","newSnow":0,"snowBottom":null,"snowTop":0,"lifts":null},{"resortName":"Hemsedal - Solheisen2022 Dec 17","searchName":"Hemsedal - Solheisen2022 Dec 17","handle":"hemsedal-solheisen2022-dec-17","newSnow":0,"snowBottom":null,"snowTop":null,"lifts":null},{"resortName":"Stryn2022 Dec 24","searchName":"Stryn2022 Dec 24","handle":"stryn2022-dec-24","newSnow":0,"snowBottom":null,"snowTop":0,"lifts":null},{"resortName":"Sauda2022 Dec 26","searchName":"Sauda2022 Dec 26","handle":"sauda2022-dec-26","newSnow":0,"snowBottom":null,"snowTop":0,"lifts":null},{"resortName":"Skeikampen2022 Dec 03","searchName":"Skeikampen2022 Dec 03","handle":"skeikampen2022-dec-03","newSnow":0,"snowBottom":0,"snowTop":0,"lifts":null},{"resortName":"Kvamskogen2023 Jan 21","searchName":"Kvamskogen2023 Jan 21","handle":"kvamskogen2023-jan-21","newSnow":0,"snowBottom":null,"snowTop":null,"lifts":null},{"resortName":"Målselv2022 Dec 30","searchName":"Malselv2022 Dec 30","handle":"malselv2022-dec-30","newSnow":0,"snowBottom":0,"snowTop":0,"lifts":null},{"resortName":"Jølster2022 Dec 10","searchName":"Jølster2022 Dec 10","handle":"jølster2022-dec-10","newSnow":0,"snowBottom":0,"snowTop":0,"lifts":null},{"resortName":"Lemonsjøen Jotunheimen2022 Dec 17","searchName":"Lemonsjøen Jotunheimen2022 Dec 17","handle":"lemonsjøen-jotunheimen2022-dec-17","newSnow":0,"snowBottom":null,"snowTop":0,"lifts":null},{"resortName":"Valdres2022 Nov 26","searchName":"Valdres2022 Nov 26","handle":"valdres2022-nov-26","newSnow":0,"snowBottom":null,"snowTop":null,"lifts":null},{"resortName":"Varingskollen2022 Dec 03","searchName":"Varingskollen2022 Dec 03","handle":"varingskollen2022-dec-03","newSnow":0,"snowBottom":0,"snowTop":0,"lifts":null},{"resortName":"Vassfjellet2022 Dec 09","searchName":"Vassfjellet2022 Dec 09","handle":"vassfjellet2022-dec-09","newSnow":0,"snowBottom":null,"snowTop":null,"lifts":null},{"resortName":"Tyin - Filefjell2022 Dec 10","searchName":"Tyin - Filefjell2022 Dec 10","handle":"tyin-filefjell2022-dec-10","newSnow":0,"snowBottom":null,"snowTop":0,"lifts":null},{"resortName":"Voss Resort2022 Dec 01","searchName":"Voss Resort2022 Dec 01","handle":"voss-resort2022-dec-01","newSnow":0,"snowBottom":0,"snowTop":0,"lifts":null},{"resortName":"Vaset2022 Dec 17","searchName":"Vaset2022 Dec 17","handle":"vaset2022-dec-17","newSnow":0,"snowBottom":null,"snowTop":null,"lifts":null},{"resortName":"Meråker2023 Jan 07","searchName":"Meraker2023 Jan 07","handle":"meraker2023-jan-07","newSnow":0,"snowBottom":null,"snowTop":0,"lifts":null},{"resortName":"Uvdal2022 Dec 03","searchName":"Uvdal2022 Dec 03","handle":"uvdal2022-dec-03","newSnow":0,"snowBottom":0,"snowTop":0,"lifts":null},{"resortName":"Vrådal2022 Dec 17","searchName":"Vradal2022 Dec 17","handle":"vradal2022-dec-17","newSnow":0,"snowBottom":null,"snowTop":null,"lifts":null},{"resortName":"Voss Fjellandsby - Myrkdalen2022 Dec 02","searchName":"Voss Fjellandsby - Myrkdalen2022 Dec 02","handle":"voss-fjellandsby-myrkdalen2022-dec-02","newSnow":0,"snowBottom":0,"snowTop":0,"lifts":null},{"resortName":"Skagahøgdi Skisenter2022 Dec 10","searchName":"Skagahøgdi Skisenter2022 Dec 10","handle":"skagahøgdi-skisenter2022-dec-10","newSnow":0,"snowBottom":0,"snowTop":0,"lifts":null},{"resortName":"Trysil2022 Dec 09","searchName":"Trysil2022 Dec 09","handle":"trysil2022-dec-09","newSnow":0,"snowBottom":0,"snowTop":0,"lifts":null}]},"Sweden":{"name":"Sweden","url":"https://www.onthesnow.co.uk/sweden/skireport","resorts":[{"resortName":"Hassela2022 Dec 23","searchName":"Hassela2022 Dec 23","handle":"hassela2022-dec-23","newSnow":0,"snowBottom":null,"snowTop":null,"lifts":null},{"resortName":"Kläppen Ski Resort2022 Dec 17","searchName":"Klappen Ski Resort2022 Dec 17","handle":"klappen-ski-resort2022-dec-17","newSnow":0,"snowBottom":null,"snowTop":null,"lifts":null},{"resortName":"Branäs2022 Dec 16","searchName":"Branas2022 Dec 16","handle":"branas2022-dec-16","newSnow":0,"snowBottom":null,"snowTop":null,"lifts":null},{"resortName":"Åre2022 Dec 02","searchName":"Are2022 Dec 02","handle":"are2022-dec-02","newSnow":0,"snowBottom":0,"snowTop":0,"lifts":null},{"resortName":"Kittelfjäll2022 Dec 10","searchName":"Kittelfjall2022 Dec 10","handle":"kittelfjall2022-dec-10","newSnow":0,"snowBottom":null,"snowTop":null,"lifts":null},{"resortName":"Hemavan2022 Nov 25","searchName":"Hemavan2022 Nov 25","handle":"hemavan2022-nov-25","newSnow":0,"snowBottom":null,"snowTop":null,"lifts":null},{"resortName":"Idre Fjäll2022 Dec 10","searchName":"Idre Fjall2022 Dec 10","handle":"idre-fjall2022-dec-10","newSnow":0,"snowBottom":0,"snowTop":0,"lifts":null},{"resortName":"Stöten in Sälen2022 Dec 09","searchName":"Stoten in Salen2022 Dec 09","handle":"stoten-in-salen2022-dec-09","newSnow":0,"snowBottom":0,"snowTop":0,"lifts":null},{"resortName":"Lofsdalen2022 Dec 16","searchName":"Lofsdalen2022 Dec 16","handle":"lofsdalen2022-dec-16","newSnow":0,"snowBottom":null,"snowTop":0,"lifts":null},{"resortName":"Ramundberget2022 Dec 17","searchName":"Ramundberget2022 Dec 17","handle":"ramundberget2022-dec-17","newSnow":0,"snowBottom":0,"snowTop":0,"lifts":null},{"resortName":"Vemdalen2022 Nov 28","searchName":"Vemdalen2022 Nov 28","handle":"vemdalen2022-nov-28","newSnow":0,"snowBottom":null,"snowTop":null,"lifts":null},{"resortName":"Sälen2022 Dec 02","searchName":"Salen2022 Dec 02","handle":"salen2022-dec-02","newSnow":0,"snowBottom":0,"snowTop":0,"lifts":null}]}}